pyluach/__init__.py
pyluach/dates.py
pyluach/gematria.py
pyluach/hebrewcal.py
pyluach/parshios.py
pyluach/utils.py
pyluach-2.1.0.dist-info/WHEEL
pyluach-2.1.0.dist-info/METADATA
pyluach-2.1.0.dist-info/RECORD
