Metadata-Version: 2.1
Name: pyluach
Version: 2.1.0
Summary: A Python package for dealing with Hebrew (Jewish) calendar dates.
Keywords: hebrew,calendar,jewish,luach,gregorian,julian,days,dates,date,conversion,parsha,holiday
Author-email: MS List <simlist@gmail.com>
Requires-Python: >=3.7
Classifier: Development Status :: 5 - Production/Stable
Classifier: Intended Audience :: Developers
Classifier: Topic :: Software Development :: Libraries :: Python Modules
Classifier: License :: OSI Approved :: MIT License
Classifier: Programming Language :: Python :: 3
Classifier: Programming Language :: Python :: 3 :: Only
Classifier: Programming Language :: Python :: 3.7
Classifier: Programming Language :: Python :: 3.8
Classifier: Programming Language :: Python :: 3.9
Classifier: Programming Language :: Python :: 3.10
Classifier: Programming Language :: Python :: 3.11
Requires-Dist: sphinx ~= 6.1.3 ; extra == "doc"
Requires-Dist: sphinx_rtd_theme ~= 1.2.0 ; extra == "doc"
Requires-Dist: pytest ; extra == "test"
Requires-Dist: pytest-cov ; extra == "test"
Requires-Dist: flake8 ; extra == "test"
Requires-Dist: beautifulsoup4 ; extra == "test"
Project-URL: Documentation, https://readthedocs.org/projects/pyluach/
Project-URL: Source, https://github.com/simlist/pyluach
Provides-Extra: doc
Provides-Extra: test
